flask_inputfilter/__init__.py
flask_inputfilter/_input_filter.cpython-312-x86_64-linux-gnu.so
flask_inputfilter/_input_filter.pxd
flask_inputfilter/_input_filter.pyx
flask_inputfilter/input_filter.py
flask_inputfilter/input_filter.pyi
flask_inputfilter/py.typed
flask_inputfilter/conditions/__init__.py
flask_inputfilter/conditions/array_length_equal_condition.py
flask_inputfilter/conditions/array_longer_than_condition.py
flask_inputfilter/conditions/base_condition.py
flask_inputfilter/conditions/custom_condition.py
flask_inputfilter/conditions/equal_condition.py
flask_inputfilter/conditions/exactly_n_of_condition.py
flask_inputfilter/conditions/exactly_n_of_matches_condition.py
flask_inputfilter/conditions/exactly_one_of_condition.py
flask_inputfilter/conditions/exactly_one_of_matches_condition.py
flask_inputfilter/conditions/integer_bigger_than_condition.py
flask_inputfilter/conditions/n_of_condition.py
flask_inputfilter/conditions/n_of_matches_condition.py
flask_inputfilter/conditions/not_equal_condition.py
flask_inputfilter/conditions/one_of_condition.py
flask_inputfilter/conditions/one_of_matches_condition.py
flask_inputfilter/conditions/required_if_condition.py
flask_inputfilter/conditions/string_longer_than_condition.py
flask_inputfilter/conditions/temporal_order_condition.py
flask_inputfilter/declarative/__init__.py
flask_inputfilter/declarative/_field_descriptor.cpython-312-x86_64-linux-gnu.so
flask_inputfilter/declarative/_field_descriptor.pxd
flask_inputfilter/declarative/_field_descriptor.pyx
flask_inputfilter/declarative/_utils.py
flask_inputfilter/declarative/cimports.pxd
flask_inputfilter/declarative/condition.py
flask_inputfilter/declarative/field.py
flask_inputfilter/declarative/field_descriptor.py
flask_inputfilter/declarative/field_descriptor.pyi
flask_inputfilter/declarative/global_filter.py
flask_inputfilter/declarative/global_validator.py
flask_inputfilter/declarative/model.py
flask_inputfilter-0.7.5.dist-info/METADATA
flask_inputfilter-0.7.5.dist-info/WHEEL
flask_inputfilter-0.7.5.dist-info/top_level.txt
flask_inputfilter-0.7.5.dist-info/RECORD
flask_inputfilter-0.7.5.dist-info/licenses/LICENSE
