Metadata-Version: 2.4
Name: flask_inputfilter
Version: 0.7.5
Summary: A library to easily filter and validate input data in Flask applications
Author-email: Leander Cain Slotosch <slotosch.leander@outlook.de>
License: MIT
Project-URL: Homepage, https://github.com/LeanderCS/flask-inputfilter
Project-URL: Documentation, https://leandercs.github.io/flask-inputfilter
Project-URL: Source, https://github.com/LeanderCS/flask-inputfilter
Project-URL: Issues, https://github.com/LeanderCS/flask-inputfilter/issues
Keywords: flask,input,validation,filter,condition,sanitization,api,data,schema,security,middleware,request,serialization,json-validation,form
Classifier: Operating System :: OS Independent
Classifier: Programming Language :: Python :: 3.14
Classifier: Programming Language :: Python :: 3.13
Classifier: Programming Language :: Python :: 3.12
Classifier: Programming Language :: Python :: 3.11
Classifier: Programming Language :: Python :: 3.10
Classifier: Programming Language :: Python :: 3.9
Classifier: Programming Language :: Python :: 3.8
Classifier: Programming Language :: Python :: 3.7
Requires-Python: >=3.7
License-File: LICENSE
Requires-Dist: flask>=2.1
Provides-Extra: dev
Requires-Dist: build; extra == "dev"
Requires-Dist: coverage; extra == "dev"
Requires-Dist: coveralls; extra == "dev"
Requires-Dist: cython; extra == "dev"
Requires-Dist: docformatter; extra == "dev"
Requires-Dist: pillow>=8.0.0; extra == "dev"
Requires-Dist: pytest; extra == "dev"
Requires-Dist: requests>=2.22.0; extra == "dev"
Requires-Dist: sphinx; extra == "dev"
Requires-Dist: sphinx-autobuild; extra == "dev"
Requires-Dist: sphinx_design; extra == "dev"
Requires-Dist: sphinx_rtd_theme; extra == "dev"
Requires-Dist: ruff; extra == "dev"
Provides-Extra: optional
Requires-Dist: pillow>=8.0.0; extra == "optional"
Requires-Dist: requests>=2.22.0; extra == "optional"
Requires-Dist: cython>=3.0; python_version <= "3.12" and extra == "optional"
Requires-Dist: cython>=3.0.12; python_version >= "3.13" and extra == "optional"
Provides-Extra: compile
Requires-Dist: cython>=3.0; python_version <= "3.12" and extra == "compile"
Requires-Dist: cython>=3.0.12; python_version >= "3.13" and extra == "compile"
Dynamic: license-file
